ufo_gleaner-0.2.2.dist-info/METADATA
ufo_gleaner-0.2.2.dist-info/WHEEL
ufo_gleaner-0.2.2.dist-info/licenses/LICENSE
ufo_gleaner/__init__.py
ufo_gleaner/ufo_gleaner.abi3.so
ufo_gleaner-0.2.2.dist-info/RECORD
