Metadata-Version: 2.4
Name: ufo_gleaner
Version: 0.2.2
Classifier: Development Status :: 4 - Beta
Classifier: License :: OSI Approved :: MIT License
Classifier: Programming Language :: Python :: 3
Classifier: Programming Language :: Python :: 3.10
Classifier: Programming Language :: Python :: 3.11
Classifier: Programming Language :: Python :: 3.12
Classifier: Programming Language :: Python :: 3.13
Classifier: Programming Language :: Python :: 3 :: Only
Classifier: Operating System :: OS Independent
Requires-Dist: cffi
License-File: LICENSE
Summary: High-performance UFO/GLIF parser for Python written in Rust
Keywords: font design,UFO
Author-email: Knut Nergaard <knut.nergaard@gmail.com>
License: LICENSE
Requires-Python: >=3.10
Project-URL: Homepage, https://github.com/knutnergaard/SMufoLib
